quickplots/__init__.py
quickplots/charts.py
quickplots/quick.py
quickplots/series.py
quickplots-2.1.0.dist-info/DESCRIPTION.rst
quickplots-2.1.0.dist-info/METADATA
quickplots-2.1.0.dist-info/RECORD
quickplots-2.1.0.dist-info/WHEEL
quickplots-2.1.0.dist-info/metadata.json
quickplots-2.1.0.dist-info/top_level.txt
